[
  { "id": 1, "name": "Atom", "imgLoc":"images/science/atom.png" },
  { "id": 2, "name": "Molecule", "imgLoc":"images/science/molecul.png" },
  { "id": 3, "name": "Gravity", "imgLoc":"images/science/gravity.png" },
  { "id": 4, "name": "Photosynthesis", "imgLoc":"images/science/Photosynthesis.png" },
  { "id": 5, "name": "DNA", "imgLoc":"images/science/dna.png" },
  { "id": 6, "name": "Cell", "imgLoc":"images/science/cell.png" },
  { "id": 7, "name": "Fossils", "imgLoc":"images/science/fossil.png" },  
  { "id": 8, "name": "Enzyme", "imgLoc":"images/science/enzyme.png" },
  { "id": 9, "name": "Neuron", "imgLoc":"images/science/neuron.png" },
  { "id": 10, "name": "Energy", "imgLoc":"images/science/energy.png" },
  { "id": 11, "name": "Chemical Reaction", "imgLoc":"images/science/chemical.png" },
  { "id": 12, "name": "Thermometer", "imgLoc":"images/science/thermometer.png" },
  { "id": 13, "name": "Hormone", "imgLoc":"images/science/Hormone.png" },

  { "id": 14, "name": "Circuit", "imgLoc":"images/science/circuit.png" },

  { "id": 15, "name": "Refraction", "imgLoc": "images/physics/refraction.png" },
  { "id": 16, "name": "Acid & Base", "imgLoc":"images/science/acidbase.png" },
  { "id": 17, "name": "Virus", "imgLoc":"images/science/virus.png" },
  { "id": 18, "name": "Voltage", "imgLoc": "images/physics/voltage.png" },
  { "id": 19, "name": "Metamorphosis", "imgLoc":"images/science/metamorphosis.png" },
  { "id": 20, "name": "Oxygen", "imgLoc":"images/science/oxygen.png" },
  { "id": 21, "name": "Carbon", "imgLoc":"images/science/carbon.png" },
  { "id": 22, "name": "Ecosystem", "imgLoc":"images/science/ecosystem.png" },
  { "id": 23, "name": "Magnetic Field", "imgLoc":"images/science/magnetic.png" },
  { "id": 24, "name": "Microscope", "imgLoc":"images/science/microscope.png" },
  { "id": 25, "name": "Bacteria", "imgLoc":"images/science/bacteria.png" },
  { "id": 26, "name": "RNA", "imgLoc":"images/science/rna.png" },
  { "id": 27, "name": "Ion", "imgLoc":"images/science/ion.png" },
  { "id": 28, "name": "Velocity", "imgLoc":"images/science/velocity.png" },
  { "id": 29, "name": "Pressure", "imgLoc":"images/science/pressure.png" },
  { "id": 30, "name": "Chloroplast", "imgLoc":"images/science/chloroplast.png" },
  { "id": 31, "name": "Mutation", "imgLoc":"images/science/mutation.png" },
  { "id": 32, "name": "Catalyst", "imgLoc":"images/science/catalyst.png" }
]
